tap_grib/__init__.py
tap_grib/__main__.py
tap_grib/client.py
tap_grib/storage.py
tap_grib/tap.py
tap_grib-1.5.0.dist-info/METADATA
tap_grib-1.5.0.dist-info/WHEEL
tap_grib-1.5.0.dist-info/entry_points.txt
tap_grib-1.5.0.dist-info/licenses/LICENSE
tap_grib-1.5.0.dist-info/RECORD
