Metadata-Version: 2.4
Name: tap-grib
Version: 1.5.0
Summary: Singer tap for Grib, built with the Meltano Singer SDK.
Author-email: Luca Capra <luca.capra@spindox.it>
License-Expression: Apache-2.0
License-File: LICENSE
Keywords: ELT,Grib
Classifier: Intended Audience :: Developers
Classifier: Operating System :: OS Independent
Classifier: Programming Language :: Python :: 3.10
Classifier: Programming Language :: Python :: 3.11
Classifier: Programming Language :: Python :: 3.12
Classifier: Programming Language :: Python :: 3.13
Classifier: Programming Language :: Python :: 3.14
Requires-Python: >=3.10
Requires-Dist: boto3>=1.39.11
Requires-Dist: pygrib>=2.1.6
Requires-Dist: s3fs>=2025.9.0
Requires-Dist: singer-sdk[faker]<0.53.0,>=0.48.1
Provides-Extra: s3
Requires-Dist: s3fs<2025.11,>=2025.9; extra == 's3'
